ReaderRaman/reader.py
ReaderRaman/settings.py
readerraman-0.1.0.dist-info/METADATA
readerraman-0.1.0.dist-info/WHEEL
readerraman-0.1.0.dist-info/RECORD
