Metadata-Version: 2.3
Name: readerraman
Version: 0.1.0
Summary: Package to load measurement from Cohaerentia Raman DTS
Author: Marco Brunero
Author-email: marco.brunero@cohaerentia.com
Requires-Python: >=3.11
Classifier: Programming Language :: Python :: 3
Classifier: Programming Language :: Python :: 3.11
Classifier: Programming Language :: Python :: 3.12
Classifier: Programming Language :: Python :: 3.13
Requires-Dist: h5py (>=3.14.0,<4.0.0)
Requires-Dist: nbformat (>=5.10.4,<6.0.0)
Requires-Dist: numpy (>=2.3.3,<3.0.0)
Requires-Dist: plotly (>=6.3.0,<7.0.0)
Requires-Dist: progress (>=1.6.1,<2.0.0)
Requires-Dist: pydantic (>=2.11.7,<3.0.0)
